nuudel_best_time_finder/__init__.py
nuudel_best_time_finder-0.2.0.dist-info/LICENSE
nuudel_best_time_finder-0.2.0.dist-info/METADATA
nuudel_best_time_finder-0.2.0.dist-info/WHEEL
nuudel_best_time_finder-0.2.0.dist-info/entry_points.txt
nuudel_best_time_finder-0.2.0.dist-info/RECORD
