Metadata-Version: 2.1
Name: nuudel-best-time-finder
Version: 0.2.0
Summary: 
License: MIT
Author: Philip Hackstock
Author-email: p.hackstock@gmail.com
Requires-Python: >=3.10,<4.0
Classifier: License :: OSI Approved :: MIT License
Classifier: Programming Language :: Python :: 3
Classifier: Programming Language :: Python :: 3.10
Classifier: Programming Language :: Python :: 3.11
Requires-Dist: pandas (>=2.0.1,<3.0.0)
Requires-Dist: requests (>=2.30.0,<3.0.0)
Requires-Dist: typer[all] (>=0.9.0,<0.10.0)
